apscale/Apscale_analyze.py
apscale/__init__.py
apscale/__main__.py
apscale/a_create_project.py
apscale/b_pe_merging.py
apscale/c_primer_trimming.py
apscale/d_quality_filtering.py
apscale/e_dereplication.py
apscale/f_denoising.py
apscale/g_swarm_clustering.py
apscale/h_replicate_merging.py
apscale/i_nc_removal.py
apscale/j_generate_read_table.py
apscale/pages/1_Add_sample_metadata.py
apscale/pages/2_Add_sequence_metadata.py
apscale/pages/3_Search_GBIF_species_names.py
apscale/pages/4_Perform_GBIF_validation.py
apscale/pages/5_Prepare_ENA_upload.py
apscale/pages/6_Export_read_tables.py
apscale-4.2.3.dist-info/licenses/LICENSE
apscale-4.2.3.dist-info/METADATA
apscale-4.2.3.dist-info/WHEEL
apscale-4.2.3.dist-info/entry_points.txt
apscale-4.2.3.dist-info/top_level.txt
apscale-4.2.3.dist-info/RECORD
