Metadata-Version: 2.4
Name: apscale
Version: 4.2.3
Summary: Advanced Pipeline for Simple yet Comprehensive AnaLysEs of DNA metabarcoding data
Home-page: https://github.com/DominikBuchner/apscale
Author: Dominik Buchner
Author-email: dominik.buchner524@googlemail.com
License: MIT
Classifier: Programming Language :: Python :: 3
Classifier: License :: OSI Approved :: MIT License
Classifier: Operating System :: OS Independent
Requires-Python: >=3.11
License-File: LICENSE
Requires-Dist: openpyxl>=3.0.10
Requires-Dist: psutil>=5.8.0
Requires-Dist: duckdb>=1.3.1
Requires-Dist: more_itertools>=10.5.0
Requires-Dist: demultiplexer2>=1.1.6
Requires-Dist: joblib>=1.0.0
Requires-Dist: biopython>=1.85
Requires-Dist: cutadapt>=5.0
Requires-Dist: tqdm>=4.56.0
Requires-Dist: fastparquet>=0.8.0
Requires-Dist: numpy>=2.0.0
Requires-Dist: pandas>=2.3.0
Requires-Dist: powerlaw>=1.5
Requires-Dist: pyarrow>=17.0.0
Requires-Dist: pygbif>=0.6.4
Requires-Dist: pyproj>=3.4.1
Requires-Dist: Shapely>=2.1.1
Requires-Dist: streamlit>=1.45.1
Requires-Dist: tables>=3.9.0
Requires-Dist: lxml-html-clean>=0.4
Requires-Dist: streamlit-autorefresh>1.0.0
Dynamic: author
Dynamic: author-email
Dynamic: classifier
Dynamic: description
Dynamic: description-content-type
Dynamic: home-page
Dynamic: license
Dynamic: license-file
Dynamic: requires-dist
Dynamic: requires-python
Dynamic: summary
